pycont/__init__.py
pycont/contract.py
pycont/template.py
pycont/asyncio/__init__.py
pycont/asyncio/contract.py
pycont/asyncio/template.py
tests/__init__.py
tests/test_async_generator.py
tests/test_generator.py
tests/test_validator.py
pycont-0.0.4.dist-info/LICENSE
pycont-0.0.4.dist-info/METADATA
pycont-0.0.4.dist-info/WHEEL
pycont-0.0.4.dist-info/top_level.txt
pycont-0.0.4.dist-info/RECORD
