Metadata-Version: 2.1
Name: pycont
Version: 0.0.4
Summary: Validate and generate data from templates
Home-page: https://github.com/AlexeyPichugin/pycont
Author: Alexey Pichugin
Author-email: a.o.pichugin@outlook.com
License: MIT License
Platform: UNKNOWN
Classifier: Development Status :: 3 - Alpha
Classifier: Intended Audience :: Developers
Classifier: License :: OSI Approved :: Apache Software License
Classifier: Topic :: Text Processing :: Filters
Classifier: Programming Language :: Python :: 3.6
Classifier: Programming Language :: Python :: 3.7
Classifier: Programming Language :: Python :: 3.8
Requires-Dist: trafaret (==2.1.0)
